ssm2eb/__init__.py
ssm2eb/__main__.py
ssm2eb/ssm2eb.py
ssm2eb/test/__init__.py
ssm2eb/test/test_ssm2eb.py
ssm2eb-0.5.2.data/scripts/ssm2eb
ssm2eb-0.5.2.dist-info/LICENSE
ssm2eb-0.5.2.dist-info/METADATA
ssm2eb-0.5.2.dist-info/WHEEL
ssm2eb-0.5.2.dist-info/top_level.txt
ssm2eb-0.5.2.dist-info/RECORD
